bump_setup
