Metadata-Version: 2.2
Name: bump-setup
Version: 1.3.0
Summary: A tool to bump the version in setup.py in python projects
Home-page: https://github.com/talwrii/bump-setup
Author: @readwithai
Author-email: talwrii@googlemail.com.com
Classifier: Programming Language :: Python :: 3
Classifier: License :: OSI Approved :: MIT License
Classifier: Operating System :: OS Independent
Requires-Python: >=3.6
License-File: LICENSE
Requires-Dist: toml
Requires-Dist: tree-sitter
Requires-Dist: tree-sitter-python
Dynamic: author
Dynamic: author-email
Dynamic: classifier
Dynamic: description
Dynamic: description-content-type
Dynamic: home-page
Dynamic: requires-dist
Dynamic: requires-python
Dynamic: summary
